nawaka/__init__.py
nawaka/groups/get_group_location.py
nawaka-0.1.0.dist-info/entry_points.txt
nawaka-0.1.0.dist-info/WHEEL
nawaka-0.1.0.dist-info/METADATA
nawaka-0.1.0.dist-info/RECORD
