Metadata-Version: 2.1
Name: nawaka
Version: 0.1.0
Summary: 
Author: Tristan de Boer
Author-email: info@tristandeboer.nl
Requires-Python: >=3.7.1,<4.0
Classifier: Programming Language :: Python :: 3
Classifier: Programming Language :: Python :: 3.8
Classifier: Programming Language :: Python :: 3.9
Requires-Dist: fuzzywuzzy (>=0.18.0,<0.19.0)
Requires-Dist: loguru (>=0.5.3,<0.6.0)
Requires-Dist: openpyxl (>=3.0.9,<4.0.0)
Requires-Dist: pandas (>=1.3.4,<2.0.0)
Requires-Dist: requests (>=2.26.0,<3.0.0)
Requires-Dist: simplekml (>=1.3.6,<2.0.0)
Requires-Dist: tqdm (>=4.62.3,<5.0.0)
